asset_discoverer/__init__.py
asset_discoverer/discoverer.py
asset_discoverer/knowledgegraph.py
models_deployer/__init__.py
models_deployer/deployment.py
models_repo/__init__.py
models_repo/management.py
tests/__init__.py
tests/test.py
parcs-19.397.dist-info/LICENSE
parcs-19.397.dist-info/METADATA
parcs-19.397.dist-info/WHEEL
parcs-19.397.dist-info/top_level.txt
parcs-19.397.dist-info/RECORD
