Metadata-Version: 2.1
Name: parcs
Version: 19.397
Summary: A framework to discover and model industrial assets
Home-page: https://gitlab.qiotec-internal.com/foresight-templates/parcs
Author: Fouad Omri
Author-email: fouad.omri@qio.io
License: UNKNOWN
Platform: UNKNOWN
Classifier: Programming Language :: Python :: 3
Classifier: License :: OSI Approved :: MIT License
Classifier: Operating System :: OS Independent
